pixel_patrol_loader_bio/config.py
pixel_patrol_loader_bio/plugin_registry.py
pixel_patrol_loader_bio/plugins/loaders/_utils.py
pixel_patrol_loader_bio/plugins/loaders/bioio_loader.py
pixel_patrol_loader_bio/plugins/loaders/zarr_loader.py
pixel_patrol_loader_bio-0.1.2.dist-info/METADATA
pixel_patrol_loader_bio-0.1.2.dist-info/WHEEL
pixel_patrol_loader_bio-0.1.2.dist-info/entry_points.txt
pixel_patrol_loader_bio-0.1.2.dist-info/top_level.txt
pixel_patrol_loader_bio-0.1.2.dist-info/RECORD
