Metadata-Version: 2.4
Name: pixel-patrol-loader-bio
Version: 0.1.2
Summary: PixelPatrol add-on package for loading images with bioio and zarr
Requires-Python: >=3.11
Requires-Dist: bioio==3.0.0
Requires-Dist: bioio-tifffile==1.3.0
Requires-Dist: bioio-ome-tiff==1.4.0
Requires-Dist: bioio-ome-zarr==2.3.0
Requires-Dist: bioio-imageio==1.3.0
Requires-Dist: pixel-patrol-base==0.1.2
Requires-Dist: zarr==3.1.1
Requires-Dist: tifffile==2025.9.9
